verilog/data_and_control_paths/GCD/gcd_control_path.v
// check the design in the 'design/' folder
module gcd_control (clock, start, less_than, equal, greater_than, sel_in, load_a, load_b, sel_a_in_x, sel_a_in_y, finish);
  input clock, start, less_than, equal, greater_than;
  output reg sel_in, load_a, load_b, sel_a_in_x, sel_a_in_y, finish;

  parameter state_start=3'b000, state_read_a=3'b001, state_read_b=3'b010, state_a_lt_b=3'b011, state_a_gt_b=3'b100, state_finish=3'b111;
  reg [2:0] cur_state;

  // need to give the load signals sime time to propagate before doing state
  // transition
  always @(posedge clock)
    case (cur_state)
      state_start: if (start) cur_state <= state_read_a;
      state_read_a: begin #1; cur_state <= state_read_b; end
      state_read_b: begin
        #1;
        if (equal) cur_state <= state_finish;
        if (less_than) cur_state <= state_a_lt_b;
        if (greater_than) cur_state <= state_a_gt_b;
      end
      state_a_lt_b: begin
        #1;
        if (equal) cur_state <= state_finish;
        if (less_than) cur_state <= state_a_lt_b;
        if (greater_than) cur_state <= state_a_gt_b;
      end
      state_a_gt_b: begin
        #1;
        if (equal) cur_state <= state_finish;
        if (less_than) cur_state <= state_a_lt_b;
        if (greater_than) cur_state <= state_a_gt_b;
      end
      state_finish: cur_state <= state_finish;
      default: cur_state <= state_start;
    endcase

  always @(cur_state)
    case (cur_state)
      state_start: begin 
        sel_in <= 1; 
        load_a <= 1;
        load_b <= 0;
        finish <= 0;
      end
      state_read_a: begin
        sel_in <= 1;
        load_a <= 0;
        load_b <= 1;
      end
      state_read_b: begin 
        load_b <= 0;
        if (less_than) begin 
          sel_in <= 0; sel_a_in_x <= 0; sel_a_in_y <= 1; 
          #1; load_b <= 1; load_a <= 0;
        end
        else if (greater_than) begin 
          sel_in <= 0; sel_a_in_x <= 1; sel_a_in_y <= 0; 
          #1; load_a <= 1; load_b <= 0;
        end
        else if (equal) finish <= 1;
      end
      state_a_lt_b: begin 
        if (less_than) begin 
          sel_in <= 0; sel_a_in_x <= 0; sel_a_in_y <= 1; 
          #1; load_b <= 1; load_a <= 0;
        end
        else if (greater_than) begin 
          sel_in <= 0; sel_a_in_x <= 1; sel_a_in_y <= 0; 
          #1; load_a <= 1; load_b <= 0;
        end
        else if (equal) finish <= 1;
      end
      state_a_gt_b: begin 
        if (less_than) begin 
          sel_in <= 0; sel_a_in_x <= 0; sel_a_in_y <= 1; 
          #1; load_b <= 1; load_a <= 0;
        end
        else if (greater_than) begin 
          sel_in <= 0; sel_a_in_x <= 1; sel_a_in_y <= 0; 
          #1; load_a <= 1; load_b <= 0;
        end
        else if (equal) finish <= 1;
      end
      state_finish: begin 
        finish <= 1; 
        load_a <= 0; load_b <= 0;
      end
      default: begin load_a <= 0; load_b <= 0; finish <= 0; end
    endcase
endmodule

hardware_design/verilog/data_and_control_paths/GCD/gcd_data_path.v
// check the design in 'design/' folder
module gcd_data (clock, data_in, sel_in, load_a, load_b, sel_a_in_x, sel_a_in_y, less_than, equal, greater_than);
  input clock, sel_in, load_a, load_b, sel_a_in_x, sel_a_in_y;
  input [15:0] data_in;
  output less_than, equal, greater_than;

  wire [15:0] bus, a_out, b_out, x, y, sub_result;

  mux load_input(data_in, sub_result, sel_in, bus);

  data_loader A(.clock(clock), .data_in(bus), .load(load_a), .data_out(a_out));
  data_loader B(.clock(clock), .data_in(bus), .load(load_b), .data_out(b_out));

  mux X(a_out, b_out, sel_a_in_x, x);
  mux Y(a_out, b_out, sel_a_in_y, y);

  comparator compare(a_out, b_out, less_than, equal, greater_than);

  subtractor subtract(x, y, sub_result);
endmodule

module data_loader(clock, data_in, load, data_out);
  input clock, load;
  input [15:0] data_in;
  output reg [15:0] data_out;

  always @(posedge clock)
  begin
    if (load) data_out = data_in;
  end
endmodule

module mux(option_a, option_b, select, out);
  input select;
  input [15:0] option_a, option_b;
  output [15:0] out;
  
  assign out = select ? option_a : option_b;
endmodule

module comparator(a, b, less_than, equal, greater_than);
  input [15:0] a, b;
  input less_than, equal, greater_than;

  assign less_than = a < b;
  assign equal = a == b;
  assign greater_than = a > b;
endmodule

module subtractor(x, y, sub_result);
  input [15:0] x, y;
  output [15:0] sub_result;
  assign sub_result = x - y;
endmodule

verilog/data_and_control_paths/GCD/test_gcd.v
module testbench;
  reg [15:0] data_in;
  reg clock, start;
  wire sel_in, finish, load_a, load_b, sel_a_in_x, sel_a_in_y, less_than, equal, greater_than;


  gcd_data data_path(
    .clock(clock),
    .data_in(data_in),
    .sel_in(sel_in),
    .load_a(load_a),
    .load_b(load_b),
    .sel_a_in_x(sel_a_in_x),
    .sel_a_in_y(sel_a_in_y),
    .less_than(less_than),
    .equal(equal),
    .greater_than(greater_than)
  );
  gcd_control control_path(
    .clock(clock),
    .finish(finish),
    .start(start),
    .sel_in(sel_in),
    .load_a(load_a),
    .load_b(load_b),
    .sel_a_in_x(sel_a_in_x),
    .sel_a_in_y(sel_a_in_y),
    .less_than(less_than),
    .equal(equal),
    .greater_than(greater_than)
  );

  always #5 clock = ~clock;

  initial 
  begin
    clock = 0;
    #2 start = 1;
    #1000 $finish;
  end

  initial 
  begin
    #12 data_in = 78;
    #10 data_in = 143;
  end

  initial
  begin
    $dumpfile("gcd_test.vcd");
    $dumpvars(0, testbench);
    $monitor("time: %4t, state: %b, A: %d, B: %d, GCD: %d, finish: %b", $time, control_path.cur_state, data_path.a_out, data_path.b_out, data_path.a_out, finish);
  end

endmodule

hardware_design/verilog/data_and_control_paths/GCD/gcd_test.vcd
$date
	Fri May 24 14:08:23 2024
$end
$version
	Icarus Verilog
$end
$timescale
	1s
$end
$scope module testbench $end
$var wire 1 ! sel_in $end
$var wire 1 " sel_a_in_y $end
$var wire 1 # sel_a_in_x $end
$var wire 1 $ load_b $end
$var wire 1 % load_a $end
$var wire 1 & less_than $end
$var wire 1 ' greater_than $end
$var wire 1 ( finish $end
$var wire 1 ) equal $end
$var reg 1 * clock $end
$var reg 16 + data_in [15:0] $end
$var reg 1 , start $end
$scope module control_path $end
$var wire 1 * clock $end
$var wire 1 , start $end
$var wire 1 & less_than $end
$var wire 1 ' greater_than $end
$var wire 1 ) equal $end
$var parameter 3 - state_a_gt_b $end
$var parameter 3 . state_a_lt_b $end
$var parameter 3 / state_finish $end
$var parameter 3 0 state_read_a $end
$var parameter 3 1 state_read_b $end
$var parameter 3 2 state_start $end
$var reg 3 3 cur_state [2:0] $end
$var reg 1 ( finish $end
$var reg 1 % load_a $end
$var reg 1 $ load_b $end
$var reg 1 # sel_a_in_x $end
$var reg 1 " sel_a_in_y $end
$var reg 1 ! sel_in $end
$upscope $end
$scope module data_path $end
$var wire 1 * clock $end
$var wire 16 4 data_in [15:0] $end
$var wire 1 % load_a $end
$var wire 1 $ load_b $end
$var wire 1 # sel_a_in_x $end
$var wire 1 " sel_a_in_y $end
$var wire 1 ! sel_in $end
$var wire 16 5 y [15:0] $end
$var wire 16 6 x [15:0] $end
$var wire 16 7 sub_result [15:0] $end
$var wire 1 & less_than $end
$var wire 1 ' greater_than $end
$var wire 1 ) equal $end
$var wire 16 8 bus [15:0] $end
$var wire 16 9 b_out [15:0] $end
$var wire 16 : a_out [15:0] $end
$scope module A $end
$var wire 1 * clock $end
$var wire 1 % load $end
$var wire 16 ; data_in [15:0] $end
$var reg 16 < data_out [15:0] $end
$upscope $end
$scope module B $end
$var wire 1 * clock $end
$var wire 1 $ load $end
$var wire 16 = data_in [15:0] $end
$var reg 16 > data_out [15:0] $end
$upscope $end
$scope module X $end
$var wire 16 ? option_a [15:0] $end
$var wire 16 @ option_b [15:0] $end
$var wire 1 # select $end
$var wire 16 A out [15:0] $end
$upscope $end
$scope module Y $end
$var wire 16 B option_a [15:0] $end
$var wire 16 C option_b [15:0] $end
$var wire 1 " select $end
$var wire 16 D out [15:0] $end
$upscope $end
$scope module compare $end
$var wire 16 E a [15:0] $end
$var wire 16 F b [15:0] $end
$var wire 1 & less_than $end
$var wire 1 ' greater_than $end
$var wire 1 ) equal $end
$upscope $end
$scope module load_input $end
$var wire 16 G option_a [15:0] $end
$var wire 1 ! select $end
$var wire 16 H out [15:0] $end
$var wire 16 I option_b [15:0] $end
$upscope $end
$scope module subtract $end
$var wire 16 J x [15:0] $end
$var wire 16 K y [15:0] $end
$var wire 16 L sub_result [15:0] $end
$upscope $end
$upscope $end
$upscope $end
$enddefinitions $end
$comment Show the parameter values. $end
$dumpall
b0 2
b10 1
b1 0
b111 /
b11 .
b100 -
$end
#0
$dumpvars
bx L
bx K
bx J
bx I
bx H
bx G
bx F
bx E
bx D
bx C
bx B
bx A
bx @
bx ?
bx >
bx =
bx <
bx ;
bx :
bx 9
bx 8
bx 7
bx 6
bx 5
bx 4
bx 3
x,
bx +
0*
x)
x(
x'
x&
x%
x$
x#
x"
x!
$end
#2
1,
#5
0(
0$
1%
1!
b0 3
1*
#10
0*
#12
b1001110 8
b1001110 ;
b1001110 =
b1001110 H
b1001110 +
b1001110 4
b1001110 G
#15
1$
0%
b1 3
b1001110 :
b1001110 <
b1001110 ?
b1001110 B
b1001110 E
1*
#20
0*
#22
b10001111 8
b10001111 ;
b10001111 =
b10001111 H
b10001111 +
b10001111 4
b10001111 G
#25
b0xx00111x 6
b0xx00111x A
b0xx00111x J
b0xx00111x 5
b0xx00111x D
b0xx00111x K
1&
0)
0'
b10001111 9
b10001111 >
b10001111 @
b10001111 C
b10001111 F
1*
#26
b1000001 7
b1000001 I
b1000001 L
b1001110 5
b1001110 D
b1001110 K
b10001111 6
b10001111 A
b10001111 J
b1000001 8
b1000001 ;
b1000001 =
b1000001 H
1"
0#
0!
0$
b10 3
#27
1$
#30
0*
#35
b1111111111110011 8
b1111111111110011 ;
b1111111111110011 =
b1111111111110011 H
b1111111111110011 7
b1111111111110011 I
b1111111111110011 L
b1000001 6
b1000001 A
b1000001 J
0&
1'
b1000001 9
b1000001 >
b1000001 @
b1000001 C
b1000001 F
1*
#36
b1101 8
b1101 ;
b1101 =
b1101 H
b1000001 5
b1000001 D
b1000001 K
b1101 7
b1101 I
b1101 L
b1001110 6
b1001110 A
b1001110 J
0"
1#
b100 3
#37
0$
1%
#40
0*
#45
b1111111111001100 8
b1111111111001100 ;
b1111111111001100 =
b1111111111001100 H
b1111111111001100 7
b1111111111001100 I
b1111111111001100 L
b1101 6
b1101 A
b1101 J
1&
0'
b1101 :
b1101 <
b1101 ?
b1101 B
b1101 E
1*
#46
b110100 8
b110100 ;
b110100 =
b110100 H
b1101 5
b1101 D
b1101 K
b110100 7
b110100 I
b110100 L
b1000001 6
b1000001 A
b1000001 J
1"
0#
b11 3
#47
0%
1$
#50
0*
#55
b100111 8
b100111 ;
b100111 =
b100111 H
b100111 7
b100111 I
b100111 L
b110100 6
b110100 A
b110100 J
b110100 9
b110100 >
b110100 @
b110100 C
b110100 F
1*
#60
0*
#65
b11010 8
b11010 ;
b11010 =
b11010 H
b11010 7
b11010 I
b11010 L
b100111 6
b100111 A
b100111 J
b100111 9
b100111 >
b100111 @
b100111 C
b100111 F
1*
#70
0*
#75
b1101 8
b1101 ;
b1101 =
b1101 H
b1101 7
b1101 I
b1101 L
b11010 6
b11010 A
b11010 J
b11010 9
b11010 >
b11010 @
b11010 C
b11010 F
1*
#80
0*
#85
b0 8
b0 ;
b0 =
b0 H
b0 7
b0 I
b0 L
b1101 6
b1101 A
b1101 J
0&
1)
b1101 9
b1101 >
b1101 @
b1101 C
b1101 F
1*
#86
0$
1(
b111 3
